{"nodes": [{"id": "fpl_optimizer_data_manager_py", "label": "data_manager.py", "file_type": "code", "source_file": "FPL_Optimizer/data_manager.py", "source_location": "L1"}, {"id": "data_manager_advancedfpldatamanager", "label": "AdvancedFPLDataManager", "file_type": "code", "source_file": "FPL_Optimizer/data_manager.py", "source_location": "L10"}, {"id": "data_manager_advancedfpldatamanager_init", "label": ".__init__()", "file_type": "code", "source_file": "FPL_Optimizer/data_manager.py", "source_location": "L13"}, {"id": "data_manager_advancedfpldatamanager_fetch_bootstrap_data", "label": ".fetch_bootstrap_data()", "file_type": "code", "source_file": "FPL_Optimizer/data_manager.py", "source_location": "L21"}, {"id": "data_manager_advancedfpldatamanager_fetch_fixtures", "label": ".fetch_fixtures()", "file_type": "code", "source_file": "FPL_Optimizer/data_manager.py", "source_location": "L45"}, {"id": "data_manager_advancedfpldatamanager_calculate_team_form", "label": ".calculate_team_form()", "file_type": "code", "source_file": "FPL_Optimizer/data_manager.py", "source_location": "L58"}, {"id": "data_manager_advancedfpldatamanager_calculate_fixture_difficulty", "label": ".calculate_fixture_difficulty()", "file_type": "code", "source_file": "FPL_Optimizer/data_manager.py", "source_location": "L100"}, {"id": "data_manager_advancedfpldatamanager_fetch_user_team", "label": ".fetch_user_team()", "file_type": "code", "source_file": "FPL_Optimizer/data_manager.py", "source_location": "L192"}, {"id": "data_manager_advancedfpldatamanager_process_enhanced_player_data", "label": ".process_enhanced_player_data()", "file_type": "code", "source_file": "FPL_Optimizer/data_manager.py", "source_location": "L226"}, {"id": "data_manager_advancedfpldatamanager_calculate_defense_score", "label": ".calculate_defense_score()", "file_type": "code", "source_file": "FPL_Optimizer/data_manager.py", "source_location": "L308"}, {"id": "data_manager_advancedfpldatamanager_calculate_comprehensive_metrics", "label": ".calculate_comprehensive_metrics()", "file_type": "code", "source_file": "FPL_Optimizer/data_manager.py", "source_location": "L342"}, {"id": "data_manager_rationale_11", "label": "Enhanced data manager with advanced metrics and fixture analysis", "file_type": "rationale", "source_file": "FPL_Optimizer/data_manager.py", "source_location": "L11"}, {"id": "data_manager_rationale_22", "label": "Fetch main FPL data with enhanced error handling", "file_type": "rationale", "source_file": "FPL_Optimizer/data_manager.py", "source_location": "L22"}, {"id": "data_manager_rationale_46", "label": "Fetch fixture data for difficulty analysis", "file_type": "rationale", "source_file": "FPL_Optimizer/data_manager.py", "source_location": "L46"}, {"id": "data_manager_rationale_59", "label": "Calculate team form based on last 5 matches (Attack & Defense)", "file_type": "rationale", "source_file": "FPL_Optimizer/data_manager.py", "source_location": "L59"}, {"id": "data_manager_rationale_101", "label": "Calculate dynamic fixture difficulty ratings for next 5 gameweeks", "file_type": "rationale", "source_file": "FPL_Optimizer/data_manager.py", "source_location": "L101"}, {"id": "data_manager_rationale_193", "label": "Fetch user's current FPL team with enhanced data", "file_type": "rationale", "source_file": "FPL_Optimizer/data_manager.py", "source_location": "L193"}, {"id": "data_manager_rationale_227", "label": "Process player data with all enhanced metrics", "file_type": "rationale", "source_file": "FPL_Optimizer/data_manager.py", "source_location": "L227"}, {"id": "data_manager_rationale_309", "label": "Calculate defensive score based on FPL 2024/25 rules", "file_type": "rationale", "source_file": "FPL_Optimizer/data_manager.py", "source_location": "L309"}, {"id": "data_manager_rationale_343", "label": "Calculate comprehensive performance metrics", "file_type": "rationale", "source_file": "FPL_Optimizer/data_manager.py", "source_location": "L343"}], "edges": [{"source": "fpl_optimizer_data_manager_py", "target": "requests", "relation": "imports", "confidence": "EXTRACTED", "source_file": "FPL_Optimizer/data_manager.py", "source_location": "L1", "weight": 1.0}, {"source": "fpl_optimizer_data_manager_py", "target": "pandas", "relation": "imports", "confidence": "EXTRACTED", "source_file": "FPL_Optimizer/data_manager.py", "source_location": "L2", "weight": 1.0}, {"source": "fpl_optimizer_data_manager_py", "target": "numpy", "relation": "imports", "confidence": "EXTRACTED", "source_file": "FPL_Optimizer/data_manager.py", "source_location": "L3", "weight": 1.0}, {"source": "fpl_optimizer_data_manager_py", "target": "collections", "relation": "imports_from", "confidence": "EXTRACTED", "source_file": "FPL_Optimizer/data_manager.py", "source_location": "L4", "weight": 1.0}, {"source": "fpl_optimizer_data_manager_py", "target": "typing", "relation": "imports_from", "confidence": "EXTRACTED", "source_file": "FPL_Optimizer/data_manager.py", "source_location": "L5", "weight": 1.0}, {"source": "fpl_optimizer_data_manager_py", "target": "fpl_optimizer_models", "relation": "imports_from", "confidence": "EXTRACTED", "source_file": "FPL_Optimizer/data_manager.py", "source_location": "L6", "weight": 1.0}, {"source": "fpl_optimizer_data_manager_py", "target": "functools", "relation": "imports_from", "confidence": "EXTRACTED", "source_file": "FPL_Optimizer/data_manager.py", "source_location": "L7", "weight": 1.0}, {"source": "fpl_optimizer_data_manager_py", "target": "time", "relation": "imports", "confidence": "EXTRACTED", "source_file": "FPL_Optimizer/data_manager.py", "source_location": "L8", "weight": 1.0}, {"source": "fpl_optimizer_data_manager_py", "target": "data_manager_advancedfpldatamanager", "relation": "contains", "confidence": "EXTRACTED", "source_file": "FPL_Optimizer/data_manager.py", "source_location": "L10", "weight": 1.0}, {"source": "data_manager_advancedfpldatamanager", "target": "data_manager_advancedfpldatamanager_init", "relation": "method", "confidence": "EXTRACTED", "source_file": "FPL_Optimizer/data_manager.py", "source_location": "L13", "weight": 1.0}, {"source": "data_manager_advancedfpldatamanager", "target": "data_manager_advancedfpldatamanager_fetch_bootstrap_data", "relation": "method", "confidence": "EXTRACTED", "source_file": "FPL_Optimizer/data_manager.py", "source_location": "L21", "weight": 1.0}, {"source": "data_manager_advancedfpldatamanager", "target": "data_manager_advancedfpldatamanager_fetch_fixtures", "relation": "method", "confidence": "EXTRACTED", "source_file": "FPL_Optimizer/data_manager.py", "source_location": "L45", "weight": 1.0}, {"source": "data_manager_advancedfpldatamanager", "target": "data_manager_advancedfpldatamanager_calculate_team_form", "relation": "method", "confidence": "EXTRACTED", "source_file": "FPL_Optimizer/data_manager.py", "source_location": "L58", "weight": 1.0}, {"source": "data_manager_advancedfpldatamanager", "target": "data_manager_advancedfpldatamanager_calculate_fixture_difficulty", "relation": "method", "confidence": "EXTRACTED", "source_file": "FPL_Optimizer/data_manager.py", "source_location": "L100", "weight": 1.0}, {"source": "data_manager_advancedfpldatamanager", "target": "data_manager_advancedfpldatamanager_fetch_user_team", "relation": "method", "confidence": "EXTRACTED", "source_file": "FPL_Optimizer/data_manager.py", "source_location": "L192", "weight": 1.0}, {"source": "data_manager_advancedfpldatamanager", "target": "data_manager_advancedfpldatamanager_process_enhanced_player_data", "relation": "method", "confidence": "EXTRACTED", "source_file": "FPL_Optimizer/data_manager.py", "source_location": "L226", "weight": 1.0}, {"source": "data_manager_advancedfpldatamanager", "target": "data_manager_advancedfpldatamanager_calculate_defense_score", "relation": "method", "confidence": "EXTRACTED", "source_file": "FPL_Optimizer/data_manager.py", "source_location": "L308", "weight": 1.0}, {"source": "data_manager_advancedfpldatamanager", "target": "data_manager_advancedfpldatamanager_calculate_comprehensive_metrics", "relation": "method", "confidence": "EXTRACTED", "source_file": "FPL_Optimizer/data_manager.py", "source_location": "L342", "weight": 1.0}, {"source": "data_manager_advancedfpldatamanager_fetch_fixtures", "target": "data_manager_advancedfpldatamanager_calculate_fixture_difficulty", "relation": "calls", "confidence": "EXTRACTED", "source_file": "FPL_Optimizer/data_manager.py", "source_location": "L52", "weight": 1.0}, {"source": "data_manager_advancedfpldatamanager_calculate_fixture_difficulty", "target": "data_manager_advancedfpldatamanager_calculate_team_form", "relation": "calls", "confidence": "EXTRACTED", "source_file": "FPL_Optimizer/data_manager.py", "source_location": "L106", "weight": 1.0}, {"source": "data_manager_advancedfpldatamanager_process_enhanced_player_data", "target": "data_manager_advancedfpldatamanager_calculate_comprehensive_metrics", "relation": "calls", "confidence": "EXTRACTED", "source_file": "FPL_Optimizer/data_manager.py", "source_location": "L306", "weight": 1.0}, {"source": "data_manager_rationale_11", "target": "data_manager_advancedfpldatamanager", "relation": "rationale_for", "confidence": "EXTRACTED", "source_file": "FPL_Optimizer/data_manager.py", "source_location": "L11", "weight": 1.0}, {"source": "data_manager_rationale_22", "target": "data_manager_advancedfpldatamanager_fetch_bootstrap_data", "relation": "rationale_for", "confidence": "EXTRACTED", "source_file": "FPL_Optimizer/data_manager.py", "source_location": "L22", "weight": 1.0}, {"source": "data_manager_rationale_46", "target": "data_manager_advancedfpldatamanager_fetch_fixtures", "relation": "rationale_for", "confidence": "EXTRACTED", "source_file": "FPL_Optimizer/data_manager.py", "source_location": "L46", "weight": 1.0}, {"source": "data_manager_rationale_59", "target": "data_manager_advancedfpldatamanager_calculate_team_form", "relation": "rationale_for", "confidence": "EXTRACTED", "source_file": "FPL_Optimizer/data_manager.py", "source_location": "L59", "weight": 1.0}, {"source": "data_manager_rationale_101", "target": "data_manager_advancedfpldatamanager_calculate_fixture_difficulty", "relation": "rationale_for", "confidence": "EXTRACTED", "source_file": "FPL_Optimizer/data_manager.py", "source_location": "L101", "weight": 1.0}, {"source": "data_manager_rationale_193", "target": "data_manager_advancedfpldatamanager_fetch_user_team", "relation": "rationale_for", "confidence": "EXTRACTED", "source_file": "FPL_Optimizer/data_manager.py", "source_location": "L193", "weight": 1.0}, {"source": "data_manager_rationale_227", "target": "data_manager_advancedfpldatamanager_process_enhanced_player_data", "relation": "rationale_for", "confidence": "EXTRACTED", "source_file": "FPL_Optimizer/data_manager.py", "source_location": "L227", "weight": 1.0}, {"source": "data_manager_rationale_309", "target": "data_manager_advancedfpldatamanager_calculate_defense_score", "relation": "rationale_for", "confidence": "EXTRACTED", "source_file": "FPL_Optimizer/data_manager.py", "source_location": "L309", "weight": 1.0}, {"source": "data_manager_rationale_343", "target": "data_manager_advancedfpldatamanager_calculate_comprehensive_metrics", "relation": "rationale_for", "confidence": "EXTRACTED", "source_file": "FPL_Optimizer/data_manager.py", "source_location": "L343", "weight": 1.0}]}